whisperpipe/__init__.py
whisperpipe/core.py
whisperpipe-0.1.0.dist-info/METADATA
whisperpipe-0.1.0.dist-info/WHEEL
whisperpipe-0.1.0.dist-info/licenses/LICENSE
whisperpipe-0.1.0.dist-info/RECORD
