Metadata-Version: 2.4
Name: whisperpipe
Version: 0.1.0
Summary: Real-time speech-to-text streaming with OpenAI Whisper
License: MIT
License-File: LICENSE
Keywords: whisper,openai,speech-to-text,stt,asr,automatic speech recognition,real-time,realtime,audio,microphone,transcription,streaming,live transcription
Author: Erfan Ramezani
Author-email: erfanramezany245@gmail.com
Requires-Python: >=3.9,<3.13
Classifier: Development Status :: 3 - Alpha
Classifier: Intended Audience :: End Users/Desktop
Classifier: Intended Audience :: Developers
Classifier: License :: OSI Approved :: MIT License
Classifier: Programming Language :: Python :: 3
Classifier: Programming Language :: Python :: 3.9
Classifier: Programming Language :: Python :: 3.10
Classifier: Programming Language :: Python :: 3.11
Classifier: Programming Language :: Python :: 3.12
Classifier: Operating System :: POSIX :: Linux
Classifier: Operating System :: Microsoft :: Windows
Classifier: Operating System :: MacOS :: MacOS X
Classifier: Environment :: Console
Classifier: Topic :: Multimedia :: Sound/Audio :: Speech
Classifier: Topic :: Multimedia :: Sound/Audio :: Capture/Recording
Classifier: Topic :: Scientific/Engineering :: Artificial Intelligence
Classifier: Topic :: Software Development :: Libraries :: Python Modules
Requires-Dist: openai-whisper (>=20240930)
Requires-Dist: pyaudio (>=0.2.14)
Requires-Dist: pynput (>=1.7.7)
Requires-Dist: sounddevice (>=0.5.2)
Project-URL: Bug Tracker, https://github.com/Erfan-ram/whisperpipe/issues
Project-URL: Changelog, https://github.com/Erfan-ram/whisperpipe/releases
Project-URL: Documentation, https://github.com/Erfan-ram/whisperpipe/blob/main/README.md
Project-URL: Homepage, https://github.com/Erfan-ram/whisperpipe
Project-URL: Repository, https://github.com/Erfan-ram/whisperpipe
Project-URL: Source, https://github.com/Erfan-ram/whisperpipe
